<?xml version="1.0" encoding="utf-8"?>
<!DOCTYPE hibernate-mapping PUBLIC "-//Hibernate/Hibernate Mapping DTD 3.0//EN"
"http://hibernate.sourceforge.net/hibernate-mapping-3.0.dtd">
<!-- 
    Mapping file autogenerated by MyEclipse Persistence Tools
-->
<hibernate-mapping>
    <class name="com.lzm.domain.Holiday" table="holiday" schema="dbo" catalog="db_oa">
        <id name="id" type="java.lang.Integer">
            <column name="id" />
            <generator class="native" />
        </id>
        <property name="proposer" type="java.lang.String">
            <column name="proposer" />
        </property>
        <property name="beginTime" type="java.sql.Timestamp">
            <column name="beginTime" length="23" />
        </property>
        <property name="endTime" type="java.sql.Timestamp">
            <column name="endTime" length="23" />
        </property>
        <property name="isCheck" type="java.lang.String">
            <column name="isCheck" not-null="true" />
        </property>
        <property name="reson" type="java.lang.String">
            <column name="reson" />
        </property>
        <property name="checker" type="java.lang.String">
            <column name="checker" />
        </property>
    </class>
</hibernate-mapping>
